gitlab_cicd_project/__init__.py
gitlab_cicd_project/main.py
gitlab_cicd_project-0.0.4.dist-info/METADATA
gitlab_cicd_project-0.0.4.dist-info/WHEEL
gitlab_cicd_project-0.0.4.dist-info/entry_points.txt
gitlab_cicd_project-0.0.4.dist-info/top_level.txt
gitlab_cicd_project-0.0.4.dist-info/RECORD
