Metadata-Version: 2.1
Name: gitlab-cicd-project
Version: 0.0.4
Summary: wifi speed test package
Home-page: UNKNOWN
Author: Shreyas Prabhakar
Author-email: shreyas.prabhakar97@gmail.com
License: UNKNOWN
Platform: UNKNOWN
Requires-Dist: twine==6.1.0
Requires-Dist: wheel==0.44.0
Requires-Dist: setuptools==57.4.0
Requires-Dist: ipywidgets==8.0.6
Requires-Dist: plotly==5.24.1
Requires-Dist: pandas==2.1.3
Requires-Dist: DateTime==5.5
Requires-Dist: psutil==6.0.0
Requires-Dist: speedtest-cli==2.1.3
Requires-Dist: jupyter==1.0.0
Requires-Dist: ipython==8.12.0
